LICENSE
README.rst
exasol/slc/__init__.py
exasol/slc/api/__init__.py
exasol/slc/api/api_errors.py
exasol/slc/api/build.py
exasol/slc/api/build_test_container.py
exasol/slc/api/clean.py
exasol/slc/api/deploy.py
exasol/slc/api/export.py
exasol/slc/api/generate_language_activation.py
exasol/slc/api/get_language_definition_builder.py
exasol/slc/api/push.py
exasol/slc/api/push_test_container.py
exasol/slc/api/run_db_tests.py
exasol/slc/api/save.py
exasol/slc/api/security_scan.py
exasol/slc/api/upload.py
exasol/slc/internal/__init__.py
exasol/slc/internal/tasks/__init__.py
exasol/slc/internal/tasks/build/__init__.py
exasol/slc/internal/tasks/build/docker_build.py
exasol/slc/internal/tasks/build/docker_flavor_build_base.py
exasol/slc/internal/tasks/build/docker_flavor_image_task.py
exasol/slc/internal/tasks/clean/__init__.py
exasol/slc/internal/tasks/clean/clean_images.py
exasol/slc/internal/tasks/export/__init__.py
exasol/slc/internal/tasks/export/cache_file_parameters.py
exasol/slc/internal/tasks/export/create_and_export_container_task.py
exasol/slc/internal/tasks/export/create_export_directory.py
exasol/slc/internal/tasks/export/export_container_base_task.py
exasol/slc/internal/tasks/export/export_container_parameters.py
exasol/slc/internal/tasks/export/export_container_task.py
exasol/slc/internal/tasks/export/export_container_tasks_creator.py
exasol/slc/internal/tasks/export/export_container_to_cache_task.py
exasol/slc/internal/tasks/export/export_container_to_file_task.py
exasol/slc/internal/tasks/export/export_containers.py
exasol/slc/internal/tasks/export/remove_cached_export_file_task.py
exasol/slc/internal/tasks/push/__init__.py
exasol/slc/internal/tasks/push/docker_push.py
exasol/slc/internal/tasks/save/__init__.py
exasol/slc/internal/tasks/save/docker_save.py
exasol/slc/internal/tasks/save/docker_save_parameter.py
exasol/slc/internal/tasks/security_scan/__init__.py
exasol/slc/internal/tasks/security_scan/security_scan.py
exasol_script_languages_container_tool-3.5.0.dist-info/LICENSE
exasol_script_languages_container_tool-3.5.0.dist-info/METADATA
exasol_script_languages_container_tool-3.5.0.dist-info/WHEEL
exasol_script_languages_container_tool-3.5.0.dist-info/entry_points.txt
exasol_script_languages_container_tool-3.5.0.dist-info/RECORD
