Metadata-Version: 2.3
Name: exasol-script-languages-container-tool
Version: 3.5.0
Summary: Script Languages Container Tool
License: MIT
Keywords: exasol,udf,script-languages
Author: Torsten Kilias
Author-email: Torsten Kilias <torsten.kilias@exasol.com>
Requires-Python: >=3.10,<3.14
Classifier: License :: OSI Approved :: MIT License
Classifier: Programming Language :: Python :: 3
Classifier: Programming Language :: Python :: 3.10
Classifier: Programming Language :: Python :: 3.11
Classifier: Programming Language :: Python :: 3.12
Classifier: Programming Language :: Python :: 3.13
Requires-Dist: click (>=8.2.1,<8.3.0)
Requires-Dist: exasol-bucketfs (>=1,<3)
Requires-Dist: exasol-integration-test-docker-environment (>=4.4.1,<6.0.0)
Requires-Dist: importlib-resources (>=6.4.0)
Requires-Dist: importlib_metadata (>=4.6.0)
Requires-Dist: jsonschema (>=4.23.0,<5.0.0)
Requires-Dist: networkx (>=3.3.0,<4.0.0)
Requires-Dist: pydantic (>=2.10.2,<3.0.0)
Project-URL: Documentation, https://github.com/exasol/script-languages-container-tool
Project-URL: Homepage, https://github.com/exasol/script-languages-container-tool
Project-URL: Repository, https://github.com/exasol/script-languages-container-tool
Project-URL: issues, https://github.com/exasol/script-languages-container-tool/issues
Project-URL: source, https://github.com/exasol/script-languages-container-tool
